drf_csv_renderer/__init__.py
drf_csv_renderer/mixins.py
drf_csv_renderer/renderers.py
drf_csv_renderer/utilities.py
drf_csv_renderer/views.py
drf_csv_renderer-0.1.6.dist-info/METADATA
drf_csv_renderer-0.1.6.dist-info/WHEEL
drf_csv_renderer-0.1.6.dist-info/RECORD
