Metadata-Version: 2.4
Name: drf-csv-renderer
Version: 0.1.6
Summary: Django REST Framework CSV renderer with configurable field flattening
Author-email: colour-white <waveafterwavetf2@gmail.com>
Maintainer-email: colour-white <waveafterwavetf2@gmail.com>
License: MIT
Keywords: CSV,csv,django,export,rest-framework
Requires-Python: >=3.12
Requires-Dist: djangorestframework>=3.16.0
